sortedness/__init__.py
sortedness/config.py
sortedness/embedding/__init__.py
sortedness/embedding/sortedness_.py
sortedness/embedding/surrogate.py
sortedness/embedding/tunning.py
sortedness/evaluation/__init__.py
sortedness/global_.py
sortedness/local.py
sortedness/misc/__init__.py
sortedness/misc/matrices.py
sortedness/misc/parallel.py
sortedness/misc/trustworthiness.py
sortedness/wtau/__init__.py
sortedness/wtau/wtau.c
sortedness/wtau/wtau.cpython-310-x86_64-linux-gnu.so
sortedness/wtau/wtau.html
sortedness/wtau/wtau.pyx
sortedness-2.231107.1.dist-info/LICENSE
sortedness-2.231107.1.dist-info/METADATA
sortedness-2.231107.1.dist-info/WHEEL
sortedness-2.231107.1.dist-info/RECORD
