Metadata-Version: 2.1
Name: sortedness
Version: 2.231107.1
Summary: Measures of projection quality
License: GPLv3
Author: davips
Author-email: dpsabc@gmail.com
Requires-Python: >=3.10,<3.13
Classifier: License :: Other/Proprietary License
Classifier: Programming Language :: Python :: 3
Classifier: Programming Language :: Python :: 3.10
Classifier: Programming Language :: Python :: 3.11
Requires-Dist: lange (>=1.230203.1,<2.0.0)
Requires-Dist: pathos (>=0.3.0,<0.4.0)
Requires-Dist: scipy (>=1.11.2,<2.0.0)
